patches/__init__.py
patches/dataframe.py
patches/types.py
pyspark_custom_types_patch-0.0.2.dist-info/LICENSE
pyspark_custom_types_patch-0.0.2.dist-info/METADATA
pyspark_custom_types_patch-0.0.2.dist-info/WHEEL
pyspark_custom_types_patch-0.0.2.dist-info/top_level.txt
pyspark_custom_types_patch-0.0.2.dist-info/RECORD
