Metadata-Version: 2.1
Name: pyspark-custom-types-patch
Version: 0.0.2
Summary: Package with workaround to handle new types in pyspark (for pyspark 3.0) 
Home-page: UNKNOWN
Author: KonstantinSk
Author-email: borondondon@gmail.com
License: UNKNOWN
Platform: UNKNOWN
Classifier: Programming Language :: Python :: 3
Classifier: Operating System :: OS Independent
Requires-Python: >=3.7
